arborator/__init__.py
arborator/constants.py
arborator/main.py
arborator/pnc.json
arborator/version.py
arborator/classes/__init__.py
arborator/classes/aggregator.py
arborator/classes/read_data.py
arborator/classes/report.py
arborator/classes/split_profiles.py
arborator-1.2.2.dist-info/licenses/LICENSE
arborator-1.2.2.dist-info/METADATA
arborator-1.2.2.dist-info/WHEEL
arborator-1.2.2.dist-info/entry_points.txt
arborator-1.2.2.dist-info/top_level.txt
arborator-1.2.2.dist-info/RECORD
