Metadata-Version: 2.4
Name: arborator
Version: 1.2.2
Summary: Arborator: Simplifying operationalized pathogen surveillance and outbreak detection
Home-page: https://github.com/phac-nml/arborator
Author: James Robertson
Author-email: james.robertson@phac-aspc.gc.ca
License: GPL-3.0-or-later
Keywords: cgMLST,wgMLST,outbreak,surveillance,clustering,distance matrix
Classifier: Development Status :: 4 - Beta
Classifier: Environment :: Console
Classifier: Intended Audience :: Science/Research
Classifier: Topic :: Scientific/Engineering
Classifier: Topic :: Scientific/Engineering :: Bio-Informatics
Classifier: Programming Language :: Python
Classifier: Programming Language :: Python :: 3.8
Classifier: Programming Language :: Python :: 3.9
Classifier: Programming Language :: Python :: 3.10
Classifier: Programming Language :: Python :: 3.11
Classifier: Programming Language :: Python :: Implementation :: CPython
Classifier: Operating System :: POSIX :: Linux
Requires-Python: >=3.8.2,<3.12
License-File: LICENSE
Requires-Dist: pyarrow>=14.0.0
Requires-Dist: fastparquet>=2023.4.0
Requires-Dist: numba<=0.61.2,>=0.57.1
Requires-Dist: numpy<2.0.0,>=1.24.4
Requires-Dist: tables>=3.8.0
Requires-Dist: six>=1.16.0
Requires-Dist: pandas<2.2.0,>=2.0.2
Requires-Dist: psutil
Requires-Dist: scipy
Requires-Dist: profile_dists
Requires-Dist: genomic_address_service>=0.3.2
Requires-Dist: openpyxl
Dynamic: author
Dynamic: author-email
Dynamic: classifier
Dynamic: home-page
Dynamic: keywords
Dynamic: license
Dynamic: license-file
Dynamic: requires-dist
Dynamic: requires-python
Dynamic: summary
